tests
spycis
