Metadata-Version: 1.1
Name: spycis
Version: 0.0.6
Summary: Console interface to stream websites
Home-page: https://github.com/marcwebbie/spycis
Author: Marcwebbie
Author-email: marcwebbie@gmail.com
License: MIT
Keywords: streaming python video download url rip convert
Platform: UNKNOWN
Classifier: Development Status :: 3 - Alpha
Classifier: Environment :: Console
Classifier: Intended Audience :: Developers
Classifier: Intended Audience :: End Users/Desktop
Classifier: Natural Language :: English
Classifier: Operating System :: OS Independent
Classifier: Programming Language :: Python
Classifier: Programming Language :: Python :: 2.7
Classifier: Programming Language :: Python :: 3
Classifier: Programming Language :: Python :: 3.3
Classifier: Topic :: Software Development :: Libraries :: Python Modules
Classifier: Topic :: Multimedia :: Video
Classifier: Topic :: Internet
